updateMondayItemLib/__init__.py
updateMondayItemLib/monday.py
updateMondayItemLib-0.1.3.dist-info/METADATA
updateMondayItemLib-0.1.3.dist-info/WHEEL
updateMondayItemLib-0.1.3.dist-info/top_level.txt
updateMondayItemLib-0.1.3.dist-info/RECORD
