Metadata-Version: 2.1
Name: updateMondayItemLib
Version: 0.1.3
Summary: Update the existing items or create new items on monday board 
Author: Bilal Ashraf
License: MIT
